{
  "version": "1.0",
  "timestamp": 1762294551301,
  "cards": [
    {
      "id": "1762294505751x5tkvfjnl",
      "x": 801,
      "y": 63,
      "fill": "#ffffff",
      "stroke": "#000000",
      "strokeWidth": 2,
      "headerBg": "#5D8BF4",
      "colorIndex": 0,
      "selected": false,
      "width": 543.4,
      "height": 364,
      "pv": "330/330pv",
      "text": "RUY68000000000",
      "historyText": "Создана большая лицензия",
      "balance": "0 / 0",
      "activePv": "0 / 0",
      "cycle": "0",
      "coinFill": "#ffd700",
      "previousPvLeft": 330,
      "showSlfBadge": false,
      "showFendouBadge": false,
      "rankBadge": null,
      "bodyHTML": "",
      "bodyGradient": "",
      "type": "large",
      "note": {
        "text": "",
        "entries": {},
        "colors": {},
        "selectedDate": "2025-11-01",
        "highlightColor": "#f44336",
        "width": 260,
        "height": 380,
        "visible": false,
        "window": null,
        "x": 0,
        "y": 0,
        "viewDate": "2025-11-01",
        "offsetX": null,
        "offsetY": null
      },
      "calculated": {
        "L": 0,
        "R": 0,
        "total": 0,
        "cycles": 0,
        "stage": 0,
        "toNext": 6
      },
      "total": 0,
      "stage": 0,
      "toNext": 6,
      "calculatedIsFull": true,
      "activePvManual": {
        "left": 0,
        "right": 0,
        "total": 0
      },
      "activePvLocal": {
        "left": 0,
        "right": 0,
        "total": 0
      },
      "activePvAggregated": {
        "left": 0,
        "right": 0,
        "total": 0,
        "remainderLeft": 0,
        "remainderRight": 0
      },
      "activePvLocalBalance": {
        "left": 0,
        "right": 0,
        "total": 0
      },
      "activePvBalance": {
        "left": 0,
        "right": 0
      },
      "activePvPacks": 0,
      "activePvCycles": 0
    },
    {
      "id": "17622945057523cujnvpha",
      "x": 1640,
      "y": 768,
      "fill": "#ffffff",
      "stroke": "#000000",
      "strokeWidth": 2,
      "headerBg": "#5D8BF4",
      "colorIndex": 0,
      "selected": false,
      "width": 418,
      "height": 280,
      "pv": "30/330pv",
      "text": "F",
      "historyText": "Создана малая лицензия",
      "balance": "0 / 0",
      "activePv": "0 / 0",
      "cycle": "0",
      "coinFill": "#3d85c6",
      "previousPvLeft": 330,
      "showSlfBadge": false,
      "showFendouBadge": false,
      "rankBadge": null,
      "bodyHTML": "",
      "bodyGradient": "",
      "type": "small",
      "note": {
        "text": "",
        "entries": {},
        "colors": {},
        "selectedDate": "2025-11-01",
        "highlightColor": "#f44336",
        "width": 260,
        "height": 380,
        "visible": false,
        "window": null,
        "x": 0,
        "y": 0,
        "viewDate": "2025-11-01",
        "offsetX": null,
        "offsetY": null
      },
      "calculated": {
        "L": 0,
        "R": 0,
        "total": 0,
        "cycles": 0,
        "stage": 0,
        "toNext": 6
      },
      "total": 0,
      "stage": 0,
      "toNext": 6,
      "calculatedIsFull": false,
      "activePvManual": {
        "left": 0,
        "right": 0,
        "total": 0
      },
      "activePvLocal": {
        "left": 0,
        "right": 0,
        "total": 0
      },
      "activePvAggregated": {
        "left": 0,
        "right": 0,
        "total": 0,
        "remainderLeft": 0,
        "remainderRight": 0
      },
      "activePvLocalBalance": {
        "left": 0,
        "right": 0,
        "total": 0
      },
      "activePvBalance": {
        "left": 0,
        "right": 0
      },
      "activePvPacks": 0,
      "activePvCycles": 0
    },
    {
      "id": "1762294505752n1b73l1ck",
      "x": 1080,
      "y": 768,
      "fill": "#ffffff",
      "stroke": "#000000",
      "strokeWidth": 2,
      "headerBg": "#5D8BF4",
      "colorIndex": 0,
      "selected": false,
      "width": 418,
      "height": 280,
      "pv": "30/330pv",
      "text": "E",
      "historyText": "Создана малая лицензия",
      "balance": "0 / 0",
      "activePv": "0 / 0",
      "cycle": "0",
      "coinFill": "#3d85c6",
      "previousPvLeft": 330,
      "showSlfBadge": false,
      "showFendouBadge": false,
      "rankBadge": null,
      "bodyHTML": "",
      "bodyGradient": "",
      "type": "small",
      "note": {
        "text": "",
        "entries": {},
        "colors": {},
        "selectedDate": "2025-11-01",
        "highlightColor": "#f44336",
        "width": 260,
        "height": 380,
        "visible": false,
        "window": null,
        "x": 0,
        "y": 0,
        "viewDate": "2025-11-01",
        "offsetX": null,
        "offsetY": null
      },
      "calculated": {
        "L": 0,
        "R": 0,
        "total": 0,
        "cycles": 0,
        "stage": 0,
        "toNext": 6
      },
      "total": 0,
      "stage": 0,
      "toNext": 6,
      "calculatedIsFull": false,
      "activePvManual": {
        "left": 0,
        "right": 0,
        "total": 0
      },
      "activePvLocal": {
        "left": 0,
        "right": 0,
        "total": 0
      },
      "activePvAggregated": {
        "left": 0,
        "right": 0,
        "total": 0,
        "remainderLeft": 0,
        "remainderRight": 0
      },
      "activePvLocalBalance": {
        "left": 0,
        "right": 0,
        "total": 0
      },
      "activePvBalance": {
        "left": 0,
        "right": 0
      },
      "activePvPacks": 0,
      "activePvCycles": 0
    },
    {
      "id": "1762294505753nfin4clu6",
      "x": 80,
      "y": 768,
      "fill": "#ffffff",
      "stroke": "#000000",
      "strokeWidth": 2,
      "headerBg": "#5D8BF4",
      "colorIndex": 0,
      "selected": false,
      "width": 418,
      "height": 280,
      "pv": "30/330pv",
      "text": "C",
      "historyText": "Создана малая лицензия",
      "balance": "0 / 0",
      "activePv": "0 / 0",
      "cycle": "0",
      "coinFill": "#3d85c6",
      "previousPvLeft": 330,
      "showSlfBadge": false,
      "showFendouBadge": false,
      "rankBadge": null,
      "bodyHTML": "",
      "bodyGradient": "",
      "type": "small",
      "note": {
        "text": "",
        "entries": {},
        "colors": {},
        "selectedDate": "2025-11-01",
        "highlightColor": "#f44336",
        "width": 260,
        "height": 380,
        "visible": false,
        "window": null,
        "x": 0,
        "y": 0,
        "viewDate": "2025-11-01",
        "offsetX": null,
        "offsetY": null
      },
      "calculated": {
        "L": 0,
        "R": 0,
        "total": 0,
        "cycles": 0,
        "stage": 0,
        "toNext": 6
      },
      "total": 0,
      "stage": 0,
      "toNext": 6,
      "calculatedIsFull": false,
      "activePvManual": {
        "left": 0,
        "right": 0,
        "total": 0
      },
      "activePvLocal": {
        "left": 0,
        "right": 0,
        "total": 0
      },
      "activePvAggregated": {
        "left": 0,
        "right": 0,
        "total": 0,
        "remainderLeft": 0,
        "remainderRight": 0
      },
      "activePvLocalBalance": {
        "left": 0,
        "right": 0,
        "total": 0
      },
      "activePvBalance": {
        "left": 0,
        "right": 0
      },
      "activePvPacks": 0,
      "activePvCycles": 0
    },
    {
      "id": "17622945057542brlm7cwj",
      "x": 632,
      "y": 768,
      "fill": "#ffffff",
      "stroke": "#000000",
      "strokeWidth": 2,
      "headerBg": "#5D8BF4",
      "colorIndex": 0,
      "selected": false,
      "width": 418,
      "height": 280,
      "pv": "30/330pv",
      "text": "D",
      "historyText": "Создана малая лицензия",
      "balance": "0 / 0",
      "activePv": "0 / 0",
      "cycle": "0",
      "coinFill": "#3d85c6",
      "previousPvLeft": 330,
      "showSlfBadge": false,
      "showFendouBadge": false,
      "rankBadge": null,
      "bodyHTML": "",
      "bodyGradient": "",
      "type": "small",
      "note": {
        "text": "",
        "entries": {},
        "colors": {},
        "selectedDate": "2025-11-01",
        "highlightColor": "#f44336",
        "width": 260,
        "height": 380,
        "visible": false,
        "window": null,
        "x": 0,
        "y": 0,
        "viewDate": "2025-11-01",
        "offsetX": null,
        "offsetY": null
      },
      "calculated": {
        "L": 0,
        "R": 0,
        "total": 0,
        "cycles": 0,
        "stage": 0,
        "toNext": 6
      },
      "total": 0,
      "stage": 0,
      "toNext": 6,
      "calculatedIsFull": false,
      "activePvManual": {
        "left": 0,
        "right": 0,
        "total": 0
      },
      "activePvLocal": {
        "left": 0,
        "right": 0,
        "total": 0
      },
      "activePvAggregated": {
        "left": 0,
        "right": 0,
        "total": 0,
        "remainderLeft": 0,
        "remainderRight": 0
      },
      "activePvLocalBalance": {
        "left": 0,
        "right": 0,
        "total": 0
      },
      "activePvBalance": {
        "left": 0,
        "right": 0
      },
      "activePvPacks": 0,
      "activePvCycles": 0
    },
    {
      "id": "1762294505755njq7rmxhv",
      "x": 360,
      "y": 448,
      "fill": "#ffffff",
      "stroke": "#000000",
      "strokeWidth": 2,
      "headerBg": "#5D8BF4",
      "colorIndex": 0,
      "selected": false,
      "width": 418,
      "height": 280,
      "pv": "30/330pv",
      "text": "A",
      "historyText": "Создана малая лицензия",
      "balance": "0 / 0",
      "activePv": "0 / 0",
      "cycle": "0",
      "coinFill": "#3d85c6",
      "previousPvLeft": 330,
      "showSlfBadge": false,
      "showFendouBadge": false,
      "rankBadge": null,
      "bodyHTML": "",
      "bodyGradient": "",
      "type": "small",
      "note": {
        "text": "",
        "entries": {},
        "colors": {},
        "selectedDate": "2025-11-01",
        "highlightColor": "#f44336",
        "width": 260,
        "height": 380,
        "visible": false,
        "window": null,
        "x": 0,
        "y": 0,
        "viewDate": "2025-11-01",
        "offsetX": null,
        "offsetY": null
      },
      "calculated": {
        "L": 0,
        "R": 0,
        "total": 0,
        "cycles": 0,
        "stage": 0,
        "toNext": 6
      },
      "total": 0,
      "stage": 0,
      "toNext": 6,
      "calculatedIsFull": false,
      "activePvManual": {
        "left": 0,
        "right": 0,
        "total": 0
      },
      "activePvLocal": {
        "left": 0,
        "right": 0,
        "total": 0
      },
      "activePvAggregated": {
        "left": 0,
        "right": 0,
        "total": 0,
        "remainderLeft": 0,
        "remainderRight": 0
      },
      "activePvLocalBalance": {
        "left": 0,
        "right": 0,
        "total": 0
      },
      "activePvBalance": {
        "left": 0,
        "right": 0
      },
      "activePvPacks": 0,
      "activePvCycles": 0
    },
    {
      "id": "1762294505755xbaxzlyya",
      "x": 1360,
      "y": 448,
      "fill": "#ffffff",
      "stroke": "#000000",
      "strokeWidth": 2,
      "headerBg": "#5D8BF4",
      "colorIndex": 0,
      "selected": false,
      "width": 418,
      "height": 280,
      "pv": "30/330pv",
      "text": "B",
      "historyText": "Создана малая лицензия",
      "balance": "0 / 0",
      "activePv": "0 / 0",
      "cycle": "0",
      "coinFill": "#3d85c6",
      "previousPvLeft": 330,
      "showSlfBadge": false,
      "showFendouBadge": false,
      "rankBadge": null,
      "bodyHTML": "",
      "bodyGradient": "",
      "type": "small",
      "note": {
        "text": "",
        "entries": {},
        "colors": {},
        "selectedDate": "2025-11-01",
        "highlightColor": "#f44336",
        "width": 260,
        "height": 380,
        "visible": false,
        "window": null,
        "x": 0,
        "y": 0,
        "viewDate": "2025-11-01",
        "offsetX": null,
        "offsetY": null
      },
      "calculated": {
        "L": 0,
        "R": 0,
        "total": 0,
        "cycles": 0,
        "stage": 0,
        "toNext": 6
      },
      "total": 0,
      "stage": 0,
      "toNext": 6,
      "calculatedIsFull": false,
      "activePvManual": {
        "left": 0,
        "right": 0,
        "total": 0
      },
      "activePvLocal": {
        "left": 0,
        "right": 0,
        "total": 0
      },
      "activePvAggregated": {
        "left": 0,
        "right": 0,
        "total": 0,
        "remainderLeft": 0,
        "remainderRight": 0
      },
      "activePvLocalBalance": {
        "left": 0,
        "right": 0,
        "total": 0
      },
      "activePvBalance": {
        "left": 0,
        "right": 0
      },
      "activePvPacks": 0,
      "activePvCycles": 0
    }
  ],
  "connections": [
    {
      "id": "1762294505756-d02vbq9",
      "from": "1762294505751x5tkvfjnl",
      "to": "1762294505755njq7rmxhv",
      "fromSide": "left",
      "toSide": "top",
      "color": "#0f62fe",
      "thickness": 5,
      "highlightType": null,
      "animationDuration": 2000
    },
    {
      "id": "1762294505756-k6bcq4k",
      "from": "1762294505751x5tkvfjnl",
      "to": "1762294505755xbaxzlyya",
      "fromSide": "right",
      "toSide": "top",
      "color": "#0f62fe",
      "thickness": 5,
      "highlightType": null,
      "animationDuration": 2000
    },
    {
      "id": "1762294505757-wtdcosw",
      "from": "1762294505755xbaxzlyya",
      "to": "1762294505752n1b73l1ck",
      "fromSide": "left",
      "toSide": "top",
      "color": "#0f62fe",
      "thickness": 5,
      "highlightType": null,
      "animationDuration": 2000
    },
    {
      "id": "1762294505758-odtx3xu",
      "from": "1762294505755xbaxzlyya",
      "to": "17622945057523cujnvpha",
      "fromSide": "right",
      "toSide": "top",
      "color": "#0f62fe",
      "thickness": 5,
      "highlightType": null,
      "animationDuration": 2000
    },
    {
      "id": "1762294505758-hcyxsbf",
      "from": "1762294505755njq7rmxhv",
      "to": "17622945057542brlm7cwj",
      "fromSide": "right",
      "toSide": "top",
      "color": "#0f62fe",
      "thickness": 5,
      "highlightType": null,
      "animationDuration": 2000
    },
    {
      "id": "1762294505759-jcicdrl",
      "from": "1762294505755njq7rmxhv",
      "to": "1762294505753nfin4clu6",
      "fromSide": "left",
      "toSide": "top",
      "color": "#0f62fe",
      "thickness": 5,
      "highlightType": null,
      "animationDuration": 2000
    }
  ],
  "connectionDefaults": {
    "color": "#0f62fe",
    "thickness": 5,
    "highlightType": null,
    "animationDuration": 2000
  },
  "canvas": {
    "backgroundColor": "#b9c4da",
    "isSelectionMode": true,
    "isHierarchicalDragMode": false,
    "guidesEnabled": true,
    "gridStep": 40,
    "isGridBackgroundVisible": true
  }
}
